brevitas/__init__.py
brevitas/common.py
brevitas/compiler.py
brevitas/config.py
brevitas/jit.py
brevitas/backport/__init__.py
brevitas/backport/_guards.py
brevitas/backport/_ops.py
brevitas/backport/fx/__init__.py
brevitas/backport/fx/_compatibility.py
brevitas/backport/fx/_pytree.py
brevitas/backport/fx/_symbolic_trace.py
brevitas/backport/fx/annotate.py
brevitas/backport/fx/config.py
brevitas/backport/fx/graph.py
brevitas/backport/fx/graph_module.py
brevitas/backport/fx/immutable_collections.py
brevitas/backport/fx/interpreter.py
brevitas/backport/fx/node.py
brevitas/backport/fx/operator_schemas.py
brevitas/backport/fx/proxy.py
brevitas/backport/fx/subgraph_rewriter.py
brevitas/backport/fx/traceback.py
brevitas/backport/fx/experimental/proxy_tensor.py
brevitas/backport/fx/experimental/symbolic_shapes.py
brevitas/backport/fx/passes/__init__.py
brevitas/backport/fx/passes/shape_prop.py
brevitas/backport/utils/_stats.py
brevitas/backport/utils/weak.py
brevitas/core/__init__.py
brevitas/core/restrict_val.py
brevitas/core/utils.py
brevitas/core/zero_point.py
brevitas/core/bit_width/__init__.py
brevitas/core/bit_width/const.py
brevitas/core/bit_width/parameter.py
brevitas/core/function_wrapper/__init__.py
brevitas/core/function_wrapper/clamp.py
brevitas/core/function_wrapper/learned_round.py
brevitas/core/function_wrapper/misc.py
brevitas/core/function_wrapper/ops_ste.py
brevitas/core/function_wrapper/shape.py
brevitas/core/function_wrapper/stochastic_round.py
brevitas/core/quant/__init__.py
brevitas/core/quant/binary.py
brevitas/core/quant/delay.py
brevitas/core/quant/float.py
brevitas/core/quant/int.py
brevitas/core/quant/int_base.py
brevitas/core/quant/ternary.py
brevitas/core/scaling/__init__.py
brevitas/core/scaling/float_scaling.py
brevitas/core/scaling/int_scaling.py
brevitas/core/scaling/pre_scaling.py
brevitas/core/scaling/runtime.py
brevitas/core/scaling/standalone.py
brevitas/core/stats/__init__.py
brevitas/core/stats/stats_op.py
brevitas-0.12.1.dist-info/LICENSE
brevitas-0.12.1.dist-info/METADATA
brevitas-0.12.1.dist-info/WHEEL
brevitas-0.12.1.dist-info/entry_points.txt
brevitas-0.12.1.dist-info/top_level.txt
brevitas-0.12.1.dist-info/RECORD
