Metadata-Version: 2.1
Name: brevitas
Version: 0.12.1
Summary: Quantization-aware training in PyTorch
Home-page: https://github.com/Xilinx/brevitas
Author: AMD Research and Advanced Development
Author-email: brevitas-external@amd.com
Requires-Python: >=3.9, <3.13
License-File: LICENSE
Requires-Dist: dependencies ==2.0.1
Requires-Dist: numpy <=1.26.4
Requires-Dist: packaging
Requires-Dist: setuptools <70.0
Requires-Dist: sympy
Requires-Dist: torch >=1.12
Requires-Dist: typing-extensions >=3.7.4
Requires-Dist: unfoldNd
Provides-Extra: dev
Requires-Dist: pre-commit ; extra == 'dev'
Provides-Extra: diffusion
Requires-Dist: accelerate ; extra == 'diffusion'
Requires-Dist: diffusers <=0.34 ; extra == 'diffusion'
Requires-Dist: pandas ; extra == 'diffusion'
Requires-Dist: torch >=2.0 ; extra == 'diffusion'
Requires-Dist: torchmetrics[image] ; extra == 'diffusion'
Requires-Dist: tqdm ; extra == 'diffusion'
Requires-Dist: transformers ; extra == 'diffusion'
Provides-Extra: docs
Requires-Dist: m2r2 ==0.3.3.post2 ; extra == 'docs'
Requires-Dist: nbsphinx ==0.9.3 ; extra == 'docs'
Requires-Dist: nbsphinx-link ==1.3.0 ; extra == 'docs'
Requires-Dist: pydata-sphinx-theme ==0.15.3 ; extra == 'docs'
Requires-Dist: sphinx ==5.3.0 ; extra == 'docs'
Requires-Dist: sphinx-autodoc-typehints ==1.21.8 ; extra == 'docs'
Requires-Dist: sphinx-gallery ==0.10.1 ; extra == 'docs'
Requires-Dist: sphinxcontrib-napoleon ==0.7 ; extra == 'docs'
Requires-Dist: sphinxemoji ==0.2.0 ; extra == 'docs'
Requires-Dist: lxml ==4.9.3 ; extra == 'docs'
Provides-Extra: export
Requires-Dist: onnx ==1.17.0 ; extra == 'export'
Requires-Dist: onnxoptimizer ; extra == 'export'
Requires-Dist: onnxscript ; extra == 'export'
Requires-Dist: qonnx ; extra == 'export'
Provides-Extra: finn_integration
Requires-Dist: bitstring ; extra == 'finn_integration'
Requires-Dist: onnx ==1.17.0 ; extra == 'finn_integration'
Requires-Dist: onnxoptimizer ; extra == 'finn_integration'
Requires-Dist: onnxruntime <1.21,>=1.15.0 ; extra == 'finn_integration'
Requires-Dist: onnxscript ; extra == 'finn_integration'
Requires-Dist: qonnx ; extra == 'finn_integration'
Requires-Dist: toposort ; extra == 'finn_integration'
Provides-Extra: hadamard
Requires-Dist: scipy ; extra == 'hadamard'
Provides-Extra: llm
Requires-Dist: accelerate ; extra == 'llm'
Requires-Dist: datasets ; extra == 'llm'
Requires-Dist: gguf ==0.17.0 ; extra == 'llm'
Requires-Dist: lm-eval ; extra == 'llm'
Requires-Dist: onnx ; extra == 'llm'
Requires-Dist: onnxruntime <1.21 ; extra == 'llm'
Requires-Dist: optimum ; extra == 'llm'
Requires-Dist: pandas ; extra == 'llm'
Requires-Dist: torch >=2.3 ; extra == 'llm'
Requires-Dist: tqdm ; extra == 'llm'
Requires-Dist: transformers[sentencepiece] ==4.50.0 ; extra == 'llm'
Provides-Extra: notebook
Requires-Dist: jupyter ; extra == 'notebook'
Requires-Dist: nbmake ; extra == 'notebook'
Provides-Extra: ort_integration
Requires-Dist: onnx ==1.17.0 ; extra == 'ort_integration'
Requires-Dist: onnxoptimizer ; extra == 'ort_integration'
Requires-Dist: onnxruntime <1.21,>=1.15.0 ; extra == 'ort_integration'
Requires-Dist: onnxscript ; extra == 'ort_integration'
Requires-Dist: qonnx ; extra == 'ort_integration'
Provides-Extra: stt
Requires-Dist: inflect ==5.6.2 ; extra == 'stt'
Requires-Dist: librosa ; extra == 'stt'
Requires-Dist: numba ; extra == 'stt'
Requires-Dist: pillow >=4.3.0 ; extra == 'stt'
Requires-Dist: requests ; extra == 'stt'
Requires-Dist: ruamel.yaml ; extra == 'stt'
Requires-Dist: soundfile ; extra == 'stt'
Requires-Dist: sox ; extra == 'stt'
Requires-Dist: torch-stft ; extra == 'stt'
Requires-Dist: tqdm ; extra == 'stt'
Requires-Dist: unidecode ; extra == 'stt'
Provides-Extra: test
Requires-Dist: hypothesis ; extra == 'test'
Requires-Dist: mock ; extra == 'test'
Requires-Dist: psutil ; extra == 'test'
Requires-Dist: pytest <8.4 ; extra == 'test'
Requires-Dist: pytest-mock ; extra == 'test'
Requires-Dist: pytest-xdist ; extra == 'test'
Requires-Dist: pytest-cases ; extra == 'test'
Requires-Dist: scipy ; extra == 'test'
Requires-Dist: torchvision ; extra == 'test'
Requires-Dist: tqdm ; extra == 'test'
Provides-Extra: tts
Requires-Dist: librosa ; extra == 'tts'
Requires-Dist: numpy ; extra == 'tts'
Requires-Dist: pillow ; extra == 'tts'
Requires-Dist: pyyaml ; extra == 'tts'
Requires-Dist: scipy ; extra == 'tts'
Requires-Dist: soundfile ; extra == 'tts'
Requires-Dist: tqdm ; extra == 'tts'
Provides-Extra: vision
Requires-Dist: accelerate ; extra == 'vision'
Requires-Dist: torch >=1.13 ; extra == 'vision'
Requires-Dist: torchvision ; extra == 'vision'
Requires-Dist: tqdm ; extra == 'vision'
